PyDefoldApi/DefoldApi.py
PyDefoldApi/__init__.py
Tests/__init__.py
Tests/test.py
pydefoldapi-1.0.9.dist-info/METADATA
pydefoldapi-1.0.9.dist-info/WHEEL
pydefoldapi-1.0.9.dist-info/top_level.txt
pydefoldapi-1.0.9.dist-info/RECORD
