Metadata-Version: 2.1
Name: pydefoldapi
Version: 1.0.9
Summary: Python Package made by Mhadhbi Issam . 
Home-page: https://gitlab.com/game-dev-comapny/libraries/pydefoldapi.git
Author: mhadhbixissam
Author-email: example@gmail.com
Classifier: Programming Language :: Python :: 3
Classifier: License :: OSI Approved :: MIT License
Classifier: Operating System :: OS Independent
Requires-Dist: PyDefold
